[
  {
    "name": "Highlights",
    "sku": "",
    "brand": "SIKU",
    "scale": "1/64",
    "price": "26,49 €*",
    "image": "https://media.siku.de/media/65/0e/e2/1770977235/10272203800_04.jpg?width=3000",
    "image_url": "https://media.siku.de/media/65/0e/e2/1770977235/10272203800_04.jpg?width=3000",
    "url": "https://www.siku.de/man-abschleppwagen-oeamtc/10272203800",
    "description": ""
  },
  {
    "name": "MAN Abschleppwagen ÖAMTC",
    "sku": "",
    "brand": "SIKU",
    "scale": "1/64",
    "price": "26,49 €*",
    "image": "",
    "image_url": "",
    "url": "https://www.siku.de/man-abschleppwagen-oeamtc/10272203800",
    "description": ""
  },
  {
    "name": "MAN Abschleppwagen ÖAMTC",
    "sku": "",
    "brand": "SIKU",
    "scale": "1/64",
    "price": "26,49 €*",
    "image": "",
    "image_url": "",
    "url": "https://www.siku.de/man-abschleppwagen-oeamtc/10272203800",
    "description": ""
  },
  {
    "name": "Kranwagen",
    "sku": "",
    "brand": "SIKU",
    "scale": "1/64",
    "price": "29,99 €*42,99 €*(30.24% gespart)",
    "image": "",
    "image_url": "",
    "url": "https://www.siku.de/kranwagen/10211000002",
    "description": ""
  },
  {
    "name": "Kranwagen",
    "sku": "",
    "brand": "SIKU",
    "scale": "1/64",
    "price": "29,99 €*42,99 €*(30.24% gespart)",
    "image": "",
    "image_url": "",
    "url": "https://www.siku.de/kranwagen/10211000002",
    "description": ""
  }
]